run_vast/__init__.py
run_vast/run_vast.py
run_vast-0.3.0.dist-info/METADATA
run_vast-0.3.0.dist-info/WHEEL
run_vast-0.3.0.dist-info/entry_points.txt
run_vast-0.3.0.dist-info/top_level.txt
run_vast-0.3.0.dist-info/RECORD
