Metadata-Version: 2.4
Name: run_vast
Version: 0.3.0
Summary: A tool for running commands on vast.ai instances
Home-page: https://github.com/andrew-healey/run_vast
Author: Andrew Healey
Author-email: doolie.healey@gmail.com
License: MIT
Classifier: Programming Language :: Python :: 3
Classifier: License :: OSI Approved :: MIT License
Classifier: Operating System :: OS Independent
Requires-Python: >=3.6
Requires-Dist: vast_api
Requires-Dist: coloredlogs
Requires-Dist: pandas
Dynamic: author
Dynamic: author-email
Dynamic: classifier
Dynamic: description
Dynamic: description-content-type
Dynamic: home-page
Dynamic: license
Dynamic: requires-dist
Dynamic: requires-python
Dynamic: summary
